Workbook
Name Slicer_Branch: #N/A
Name Slicer_Category: #N/A
Name Slicer_Months__Date: #N/A
Name Slicer_Payment_Method: #N/A

Sheet Dashboard

Sheet Pivot_Tables
A3: Branch | B3: Total Revenue
A4: EASTLANDS | B4: 176604.05 | D4: =A4 -> EASTLANDS | E4: =B4 -> 176604.05
A5: NAIROBI CBD | B5: 175508.51 | D5: =A5 -> NAIROBI CBD | E5: =B5 -> 175508.51 | G5: Total Rev | H5: =SUM(B4:B8) -> 849745.31
A6: NGONG ROAD | B6: 151945.73 | D6: =A6 -> NGONG ROAD | E6: =B6 -> 151945.73
A7: THIKA ROAD | B7: 166520.34 | D7: =A7 -> THIKA ROAD | E7: =B7 -> 166520.34
A8: WESTLANDS | B8: 179166.68 | D8: =A8 -> WESTLANDS | E8: =B8 -> 179166.68
A11: Category | B11: Total Revenue
A12: Bakery | B12: 78728.97 | D12: =A12 -> Bakery | E12: =B12 -> 78728.97 | G12: Max: | H12: =MAX(B12:B17) -> 254618.84
A13: Dairy | B13: 155365.6 | D13: =A13 -> Dairy | E13: =B13 -> 155365.6 | H13: =_xlfn.XLOOKUP(H12,B12:B17,A12:A17,0,0) -> Household
A14: Grocery | B14: 81580.61 | D14: =A14 -> Grocery | E14: =B14 -> 81580.61
A15: Household | B15: 254618.84 | D15: =A15 -> Household | E15: =B15 -> 254618.84
A16: Personal Care | B16: 73813.33 | D16: =A16 -> Personal Care | E16: =B16 -> 73813.33
A17: Produce | B17: 205637.96 | D17: =A17 -> Produce | E17: =B17 -> 205637.96
A20: Item | B20: Total Revenue
A21: Milk | B21: 155365.6 | D21: =A21 -> Milk | E21: =B21 -> 155365.6
A22: Sugar | B22: 116690.81 | D22: =A22 -> Sugar | E22: =B22 -> 116690.81
A23: Salt | B23: 84557.08 | D23: =A23 -> Salt | E23: =B23 -> 84557.08
A24: Rice | B24: 82662.29 | D24: =A24 -> Rice | E24: =B24 -> 82662.29
A25: Cooking Oil | B25: 81580.61 | D25: =A25 -> Cooking Oil | E25: =B25 -> 81580.61
A26: Bread | B26: 78728.97 | D26: =A26 -> Bread | E26: =B26 -> 78728.97
A27: Eggs | B27: 53577.87 | D27: =A27 -> Eggs | E27: =B27 -> 53577.87
A28: Shampoo | B28: 36964.91 | D28: =A28 -> Shampoo | E28: =B28 -> 36964.91
A29: Toothpaste | B29: 36848.42 | D29: =A29 -> Toothpaste | E29: =B29 -> 36848.42
A30: Tomatoes | B30: 35303.53 | D30: =A30 -> Tomatoes | E30: =B30 -> 35303.53
A31: Onions | B31: 34094.27 | D31: =A31 -> Onions | E31: =B31 -> 34094.27
A32: Tissue | B32: 29198.61 | D32: =A32 -> Tissue | E32: =B32 -> 29198.61
A33: Laundry Soap | B33: 24172.34 | D33: =A33 -> Laundry Soap | E33: =B33 -> 24172.34
A38: Branch | B38: Payment_Method | C38: Total Revenue
A39: EASTLANDS | B39: Card | C39: 76356.33
B40: Cash | C40: 52337.45
B41: Mobile | C41: 47910.27
A42: NAIROBI CBD | B42: Card | C42: 69261.88
B43: Mobile | C43: 56027.26
B44: Cash | C44: 50219.37
A45: NGONG ROAD | B45: Cash | C45: 61514.67
B46: Card | C46: 49811.77
B47: Mobile | C47: 40619.29
A48: THIKA ROAD | B48: Cash | C48: 63298.42
B49: Mobile | C49: 51920.8
B50: Card | C50: 51301.12
A51: WESTLANDS | B51: Mobile | C51: 70319.23
B52: Cash | C52: 57491.7
B53: Card | C53: 51355.75
A56: Branch | B56: Category | C56: Sum of Revenue
A57: EASTLANDS | B57: Bakery | C57: 13254.29
B58: Dairy | C58: 45083.32
B59: Grocery | C59: 12292.46
B60: Household | C60: 56857.46
B61: Personal Care | C61: 12063.23
B62: Produce | C62: 37053.29
A63: NAIROBI CBD | B63: Bakery | C63: 17358.19
B64: Dairy | C64: 13587.3
B65: Grocery | C65: 14540.79
B66: Household | C66: 69644.24
B67: Personal Care | C67: 13022.49
B68: Produce | C68: 47355.5
A69: NGONG ROAD | B69: Bakery | C69: 14595.08
B70: Dairy | C70: 25668.42
B71: Grocery | C71: 17269.78
B72: Household | C72: 40486.29
B73: Personal Care | C73: 18899.06
B74: Produce | C74: 35027.1
A75: THIKA ROAD | B75: Bakery | C75: 20994.57
B76: Dairy | C76: 27383.93
B77: Grocery | C77: 21228.33
B78: Household | C78: 35548.58
B79: Personal Care | C79: 18972.55
B80: Produce | C80: 42392.38
A81: WESTLANDS | B81: Bakery | C81: 12526.84
B82: Dairy | C82: 43642.63
B83: Grocery | C83: 16249.25
B84: Household | C84: 52082.27
B85: Personal Care | C85: 10856
B86: Produce | C86: 43809.69
A89: Months | B89: Total Revenue
A90: Jan | B90: 70185.44 | D90: =A90 -> Jan | E90: =B90 -> 70185.44
A91: Feb | B91: 79951.07 | D91: =A91 -> Feb | E91: =B91 -> 79951.07 | G91: Max: | H91: =MAX(B90:B100) -> 110909.29
A92: Mar | B92: 93550.78 | D92: =A92 -> Mar | E92: =B92 -> 93550.78 | H92: =_xlfn.XLOOKUP(H91,B90:B100,A90:A100,0,0) -> Aug
A93: Apr | B93: 67106.75 | D93: =A93 -> Apr | E93: =B93 -> 67106.75
A94: May | B94: 56554.19 | D94: =A94 -> May | E94: =B94 -> 56554.19
A95: Jun | B95: 68937.99 | D95: =A95 -> Jun | E95: =B95 -> 68937.99
A96: Jul | B96: 71978.02 | D96: =A96 -> Jul | E96: =B96 -> 71978.02
A97: Aug | B97: 110909.29 | D97: =A97 -> Aug | E97: =B97 -> 110909.29
A98: Sept | B98: 72711.16 | D98: =A98 -> Sept | E98: =B98 -> 72711.16
A99: Oct | B99: 87030.31 | D99: =A99 -> Oct | E99: =B99 -> 87030.31
A100: Nov | B100: 70830.31 | D100: =A100 -> Nov | E100: =B100 -> 70830.31
A103: Payment_Method | B103: Total Revenue
A104: Card | B104: 298086.85 | D104: =A104 -> Card | E104: =B104 -> 298086.85
A105: Cash | B105: 284861.61 | D105: =A105 -> Cash | E105: =B105 -> 284861.61
A106: Mobile | B106: 266796.85 | D106: =A106 -> Mobile | E106: =B106 -> 266796.85

Sheet Clean_Data
A1: Date | B1: Receipt_ID | C1: Branch | D1: Item | E1: Category | F1: Quantity | G1: Unit_Price | H1: Payment_Method | I1: Revenue
A2: 45619 | B2: R1028 | C2: NAIROBI CBD | D2: Onions | E2: {=_xlfn.XLOOKUP(D2,_xlfn.ANCHORARRAY('Item_ Master'!$A$2),'Item_ Master'!$B$2:$B$14,0,0)} -> Produce | F2: 5 | G2: 184.69 | H2: Cash | I2: =F2*$G$2 -> 923.45
A3: 45571 | B3: R1022 | C3: NGONG ROAD | D3: Cooking Oil | E3: {=_xlfn.XLOOKUP(D3,_xlfn.ANCHORARRAY('Item_ Master'!$A$2),'Item_ Master'!$B$2:$B$14,0,0)} -> Grocery | F3: 1 | G3: 66.39 | H3: Cash | I3: =F3*G3 -> 66.39
A4: 45600 | B4: R1006 | C4: NGONG ROAD | D4: Bread | E4: {=_xlfn.XLOOKUP(D4,_xlfn.ANCHORARRAY('Item_ Master'!$A$2),'Item_ Master'!$B$2:$B$14,0,0)} -> Bakery | F4: 9 | G4: 280.74 | H4: Card | I4: =F4*G4 -> 2526.66
A5: 45295 | B5: R1194 | C5: WESTLANDS | D5: Tomatoes | E5: {=_xlfn.XLOOKUP(D5,_xlfn.ANCHORARRAY('Item_ Master'!$A$2),'Item_ Master'!$B$2:$B$14,0,0)} -> Produce | F5: 7 | G5: 237.14 | H5: Cash | I5: =F5*G5 -> 1659.98
A6: 45464 | B6: R1026 | C6: NAIROBI CBD | D6: Cooking Oil | E6: {=_xlfn.XLOOKUP(D6,_xlfn.ANCHORARRAY('Item_ Master'!$A$2),'Item_ Master'!$B$2:$B$14,0,0)} -> Grocery | F6: 2 | G6: 247.44 | H6: Card | I6: =F6*G6 -> 494.88
A7: 45314 | B7: R1186 | C7: THIKA ROAD | D7: Laundry Soap | E7: {=_xlfn.XLOOKUP(D7,_xlfn.ANCHORARRAY('Item_ Master'!$A$2),'Item_ Master'!$B$2:$B$14,0,0)} -> Household | F7: 1 | G7: 585.21 | H7: Card | I7: =F7*G7 -> 585.21
A8: 45442 | B8: R1160 | C8: NGONG ROAD | D8: Rice | E8: {=_xlfn.XLOOKUP(D8,_xlfn.ANCHORARRAY('Item_ Master'!$A$2),'Item_ Master'!$B$2:$B$14,0,0)} -> Produce | F8: 10 | G8: 155.76 | H8: Cash | I8: =F8*G8 -> 1557.6
A9: 45408 | B9: R1197 | C9: EASTLANDS | D9: Milk | E9: {=_xlfn.XLOOKUP(D9,_xlfn.ANCHORARRAY('Item_ Master'!$A$2),'Item_ Master'!$B$2:$B$14,0,0)} -> Dairy | F9: 4 | G9: 526.57 | H9: Card | I9: =F9*G9 -> 2106.28
A10: 45617 | B10: R1093 | C10: WESTLANDS | D10: Rice | E10: {=_xlfn.XLOOKUP(D10,_xlfn.ANCHORARRAY('Item_ Master'!$A$2),'Item_ Master'!$B$2:$B$14,0,0)} -> Produce | F10: 6 | G10: 165.23 | H10: Card | I10: =F10*G10 -> 991.38
A11: 45328 | B11: R1155 | C11: WESTLANDS | D11: Laundry Soap | E11: {=_xlfn.XLOOKUP(D11,_xlfn.ANCHORARRAY('Item_ Master'!$A$2),'Item_ Master'!$B$2:$B$14,0,0)} -> Household | F11: 4 | G11: 139.87 | H11: Card | I11: =F11*G11 -> 559.48
A12: 45619 | B12: R1176 | C12: NGONG ROAD | D12: Sugar | E12: {=_xlfn.XLOOKUP(D12,_xlfn.ANCHORARRAY('Item_ Master'!$A$2),'Item_ Master'!$B$2:$B$14,0,0)} -> Household | F12: 6 | G12: 513.57 | H12: Cash | I12: =F12*G12 -> 3081.42
A13: 45308 | B13: R1080 | C13: THIKA ROAD | D13: Sugar | E13: {=_xlfn.XLOOKUP(D13,_xlfn.ANCHORARRAY('Item_ Master'!$A$2),'Item_ Master'!$B$2:$B$14,0,0)} -> Household | F13: 2 | G13: 166.04 | H13: Mobile | I13: =F13*G13 -> 332.08
A14: 45453 | B14: R1054 | C14: THIKA ROAD | D14: Cooking Oil | E14: {=_xlfn.XLOOKUP(D14,_xlfn.ANCHORARRAY('Item_ Master'!$A$2),'Item_ Master'!$B$2:$B$14,0,0)} -> Grocery | F14: 8 | G14: 128.58 | H14: Cash | I14: =F14*G14 -> 1028.64
... A501: 45361 | B501: R1199 | C501: NGONG ROAD | D501: Toothpaste | E501: {=_xlfn.XLOOKUP(D501,_xlfn.ANCHORARRAY('Item_ Master'!$A$2),'Item_ Master'!$B$2:$B$14,0,0)} -> Personal Care | F501: 1 | G501: 145.56 | H501: Cash | I501: =F501*G501 -> 145.56

Sheet Item_ Master
A1: Item | B1: Category
A2: {=_xlfn.UNIQUE('Clean_Data'!D2:$D$501,FALSE)} -> Onions | B2: Produce
A3: Cooking Oil | B3: Grocery
A4: Bread | B4: Bakery
A5: Tomatoes | B5: Produce
A6: Laundry Soap | B6: Household
A7: Rice | B7: Produce
A8: Milk | B8: Dairy
A9: Sugar | B9: Household
A10: Eggs | B10: Produce
A11: Shampoo | B11: Personal Care
A12: Tissue | B12: Household
A13: Salt | B13: Household
A14: Toothpaste | B14: Personal Care

Sheet Raw_Data
A1: Date | B1: Receipt_ID | C1: Branch | D1: Item | E1: Category | F1: Quantity | G1: Unit_Price | H1: Payment_Method
A2: 45619 | B2: R1028 | C2: Nairobi CBD | D2: Onions | E2: Produce | F2: 5 | G2: 184.69 | H2: Cash
A3: 45571 | B3: R1022 | C3: Ngong Road | D3: Oil 2L | E3: Grocery | F3: 1 | G3: 66.39 | H3: Cash
A4: 45600 | B4: R1006 | C4: Ngong Road | D4: brown bread | E4: Bakery | F4: 9 | G4: 280.74 | H4: Card
A5: 45295 | B5: R1194 | C5: Westlands | D5: Tomatoes | E5: Produce | F5: 7 | G5: 237.14 | H5: Cash
A6: 45464 | B6: R1026 | C6: Nairobi CBD | D6: Cooking Oil | E6: Grocery | F6: 2 | G6: 247.44 | H6: Card
A7: 45314 | B7: R1186 | C7: Thika Road | D7: Laundry Soap | F7: 2 | G7: 585.21 | H7: Card
A8: 45442 | B8: R1160 | C8: Ngong Road | D8: Rice 5kg | F8: 10 | G8: 155.76 | H8: Cash
A9: 45408 | B9: R1197 | C9: Eastlands | D9: MILK | E9: Dairy | F9: 4 | G9: 526.57 | H9: Card
A10: 45617 | B10: R1093 | C10: Westlands | D10: Rice 5kg | E10: Grocery | F10: 6 | G10: 165.23 | H10: Card
A11: 45328 | B11: R1155 | C11: Westlands | D11: Laundry Soap | E11: Household | F11: 4 | G11: 139.87 | H11: Card
A12: 45619 | B12: R1176 | C12: Ngong Road | D12: Sugar | E12: Grocery | F12: 6 | G12: 513.57 | H12: Cash
A13: 45308 | B13: R1080 | C13: Thika Road | D13: Sugar 1kg | E13: Grocery | F13: 2 | G13: 166.04 | H13: Mobile
A14: 45453 | B14: R1054 | C14: Thika Road | D14: Cooking Oil | E14: Grocery | F14: 8 | G14: 128.58 | H14: Cash
A15: 45579 | B15: R1137 | C15: Eastlands | D15: Onions | E15: Produce | F15: 10 | G15: 285.64 | H15: Mobile
A16: 45404 | B16: R1035 | C16: Ngong Road | D16: Eggs Tray | E16: Dairy | F16: 2 | G16: 465.68 | H16: Cash
A17: 45373 | B17: R1174 | C17: Thika Road | D17: Shampoo | E17: Personal Care | F17: 2 | G17: 261.62 | H17: Mobile
A18: 45562 | B18: R1064 | C18: Ngong Road | D18: Milk | E18: Dairy | F18: 2 | G18: 424.94 | H18: Mobile
A19: 45620 | B19: R1087 | C19: Nairobi CBD | D19: SUGAR | E19: Grocery | F19: 7 | G19: 136.99 | H19: Cash
A20: 45426 | B20: R1128 | C20: Westlands | D20: Soap | E20: Household | F20: 2 | G20: 528.79 | H20: Card
... A26: 45451 | B26: R1102 | C26: Eastlands | D26: Eggs | E26: Dairy | F26: 9 | G26: 298.32 | H26: Cash
A27: 45465 | B27: R1005 | C27: Ngong Road | D27: Laundry Soap | F27: 4 | G27: 373.64 | H27: Cash
A28: 45615 | B28: R1015 | C28: Westlands | D28: MILK | E28: Dairy | F28: 1 | G28: 522.8 | H28: Cash
A29: 45434 | B29: R1171 | C29: Thika Road | D29: brown bread | E29: Bakery | F29: 9 | G29: 122.77 | H29: Mobile
A30: 45416 | B30: R1200 | C30: Thika Road | D30: Oil 2L | E30: Grocery | F30: 4 | G30: 101.88 | H30: Mobile
A31: 45508 | B31: R1105 | C31: Thika Road | D31: Onions | F31: 1 | G31: 420.35 | H31: Mobile
A32: 45498 | B32: R1186 | C32: Eastlands | D32: Milk 1L | E32: Dairy | F32: 4 | G32: 155.37 | H32: Mobile
A33: 45508 | B33: R1046 | C33: Eastlands | D33: Eggs | E33: Dairy | F33: 4 | G33: 530.97 | H33: Cash
A34: 45573 | B34: R1025 | C34: Nairobi CBD | D34: Salt | E34: Grocery | F34: 9 | G34: 509.82 | H34: Cash
A35: 45413 | B35: R1042 | C35: Thika Road | D35: Eggs Tray | E35: Dairy | F35: 8 | G35: 167.56 | H35: Card
A36: 45376 | B36: R1097 | C36: Nairobi CBD | D36: Cooking Oil | E36: Grocery | F36: 5 | G36: 559.58 | H36: Card
A37: 45576 | B37: R1169 | C37: Thika Road | D37: Bread | E37: Bakery | F37: 4 | G37: 213.19 | H37: Cash
A38: 45569 | B38: R1015 | C38: Eastlands | D38: milk | E38: Dairy | F38: 1 | G38: 371.3 | H38: Mobile
A39: 45563 | B39: R1040 | C39: Nairobi CBD | D39: Soap | E39: Household | F39: 2 | G39: 518.24 | H39: Cash
A40: 45412 | B40: R1103 | C40: Nairobi CBD | D40: Toothpaste | E40: Personal Care | F40: 4 | G40: 368.41 | H40: Cash
A41: 45506 | B41: R1168 | C41: Ngong Road | D41: Toothpaste | E41: Personal Care | F41: 9 | G41: 224 | H41: Card
A42: 45452 | B42: R1061 | C42: Eastlands | D42: Cooking Oil | E42: Grocery | F42: 3 | G42: 419.43 | H42: Card
A43: 45329 | B43: R1002 | C43: Thika Road | D43: Shampoo | E43: Personal Care | F43: 10 | G43: 597.85 | H43: Cash
... A48: 45318 | B48: R1023 | C48: Thika Road | D48: Sugar 1kg | E48: Grocery | F48: 1 | G48: 51.95 | H48: Cash
A49: 45426 | B49: R1041 | C49: Thika Road | D49: Laundry Soap | F49: 7 | G49: 358.5 | H49: Cash
A50: 45368 | B50: R1139 | C50: Nairobi CBD | D50: Rice 5kg | F50: 10 | G50: 353.89 | H50: Card
A51: 45449 | B51: R1093 | C51: Nairobi CBD | D51: Rice 5kg | F51: 4 | G51: 425.14 | H51: Mobile
A52: 45578 | B52: R1104 | C52: Ngong Road | D52: Onions | E52: Produce | F52: 3 | G52: 559.17 | H52: Cash
A53: 45382 | B53: R1105 | C53: Nairobi CBD | D53: White Bread | E53: Bakery | F53: 6 | G53: 480.31 | H53: Card
A54: 45419 | B54: R1068 | C54: Westlands | D54: Tomatoes | E54: Produce | F54: 2 | G54: 260.4 | H54: Cash
A55: 45405 | B55: R1051 | C55: Thika Road | D55: Rice 5kg | E55: Grocery | F55: 5 | G55: 501.3 | H55: Cash
A56: 45390 | B56: R1102 | C56: Eastlands | D56: Sugar 1kg | E56: Grocery | F56: 2 | G56: 581.79 | H56: Card
A57: 45552 | B57: R1102 | C57: Ngong Road | D57: Rice | E57: Grocery | F57: 1 | G57: 113.44 | H57: Card
A58: 45427 | B58: R1009 | C58: Nairobi CBD | D58: Shampoo | E58: Personal Care | F58: 7 | G58: 240.13 | H58: Card
A59: 45553 | B59: R1029 | C59: Thika Road | D59: Toothpaste | E59: Personal Care | F59: 4 | G59: 190.1 | H59: Mobile
A60: 45558 | B60: R1137 | C60: Westlands | D60: Rice 5kg | E60: Grocery | F60: 7 | G60: 88.49 | H60: Mobile
A61: 45611 | B61: R1080 | C61: Nairobi CBD | D61: Onions | E61: Produce | F61: 5 | G61: 328.92 | H61: Mobile
A62: 45498 | B62: R1178 | C62: Eastlands | D62: Laundry Soap | E62: Household | F62: 3 | G62: 155.51 | H62: Mobile
A63: 45381 | B63: R1157 | C63: Ngong Road | D63: SUGAR | E63: Grocery | F63: 7 | G63: 351.37 | H63: Cash
... A65: 45553 | B65: R1121 | C65: Westlands | D65: Salt 500g | E65: Grocery | F65: 2 | G65: 206.08 | H65: Mobile
A66: 45463 | B66: R1023 | C66: Westlands | D66: Salt 500g | F66: 5 | G66: 173.55 | H66: Cash
A67: 45315 | B67: R1062 | C67: Thika Road | D67: Shampoo | E67: Personal Care | F67: 2 | G67: 300.48 | H67: Mobile
A68: 45488 | B68: R1126 | C68: Thika Road | D68: Sugar | E68: Grocery | F68: 3 | G68: 410.83 | H68: Cash
A69: 45346 | B69: R1199 | C69: Thika Road | D69: Sugar | E69: Grocery | F69: 3 | G69: 492.26 | H69: Mobile
A70: 45317 | B70: R1142 | C70: Westlands | D70: Milk 1L | E70: Dairy | F70: 8 | G70: 123.34 | H70: Card
A71: 45578 | B71: R1152 | C71: Eastlands | D71: Eggs | E71: Dairy | F71: 10 | G71: 498.25 | H71: Mobile
A72: 45572 | B72: R1114 | C72: Westlands | D72: Onions | E72: Produce | F72: 8 | G72: 297.54 | H72: Cash
A73: 45433 | B73: R1196 | C73: Ngong Road | D73: Eggs Tray | E73: Dairy | F73: 4 | G73: 201.03 | H73: Cash
A74: 45412 | B74: R1069 | C74: Eastlands | D74: Rice | E74: Grocery | F74: 9 | G74: 94.32 | H74: Cash
A75: 45370 | B75: R1180 | C75: Westlands | D75: MILK | E75: Dairy | F75: 7 | G75: 274.18 | H75: Mobile
A76: 45323 | B76: R1052 | C76: Thika Road | D76: Cooking Oil | E76: Grocery | F76: 10 | G76: 570.33 | H76: Cash
A77: 45586 | B77: R1097 | C77: Thika Road | D77: Milk | E77: Dairy | F77: 6 | G77: 214.24 | H77: Card
A78: 45506 | B78: R1137 | C78: Ngong Road | D78: Shampoo | E78: Personal Care | F78: 4 | G78: 318.53 | H78: Card
A79: 45306 | B79: R1099 | C79: Eastlands | D79: Salt 500g | E79: Grocery | F79: 7 | G79: 448.3 | H79: Card
A80: 45610 | B80: R1136 | C80: Nairobi CBD | D80: Cooking Oil | F80: 10 | G80: 360.42 | H80: Cash
A81: 45511 | B81: R1034 | C81: Thika Road | D81: White Bread | E81: Bakery | F81: 1 | G81: 193.09 | H81: Card
A82: 45459 | B82: R1086 | C82: Thika Road | D82: Sugar 1kg | E82: Grocery | F82: 7 | G82: 188.75 | H82: Cash
A83: 45568 | B83: R1013 | C83: Eastlands | D83: Sugar | F83: 2 | G83: 479.68 | H83: Mobile
A84: 45307 | B84: R1063 | C84: Westlands | D84: Milk | E84: Dairy | F84: 10 | G84: 133.81 | H84: Cash
A85: 45350 | B85: R1144 | C85: Westlands | D85: Eggs | E85: Dairy | F85: 5 | G85: 471.79 | H85: Cash
A86: 45350 | B86: R1199 | C86: Westlands | D86: SUGAR | E86: Grocery | F86: 2 | G86: 368.28 | H86: Card
A87: 45484 | B87: R1101 | C87: Westlands | D87: MILK | E87: Dairy | F87: 10 | G87: 429.84 | H87: Mobile
A88: 45446 | B88: R1175 | C88: Ngong Road | D88: Milk 1L | E88: Dairy | F88: 10 | G88: 480.45 | H88: Card
A89: 45481 | B89: R1017 | C89: Ngong Road | D89: Salt | E89: Grocery | F89: 6 | G89: 56.96 | H89: Card
A90: 45346 | B90: R1110 | C90: Eastlands | D90: Salt | E90: Grocery | F90: 8 | G90: 439.02 | H90: Card
A91: 45559 | B91: R1166 | C91: Eastlands | D91: Shampoo | E91: Personal Care | F91: 9 | G91: 476.05 | H91: Card
A92: 45595 | B92: R1068 | C92: Eastlands | D92: Sugar | E92: Grocery | F92: 2 | G92: 203.41 | H92: Card
A93: 45529 | B93: R1145 | C93: Ngong Road | D93: Salt 500g | E93: Grocery | F93: 7 | G93: 235.02 | H93: Card
A94: 45385 | B94: R1124 | C94: Westlands | D94: Rice 5kg | E94: Grocery | F94: 5 | G94: 237.19 | H94: Mobile
A95: 45433 | B95: R1142 | C95: Nairobi CBD | D95: Soap | E95: Household | F95: 4 | G95: 97.09 | H95: Mobile
... A110: 45380 | B110: R1141 | C110: Nairobi CBD | D110: White Bread | E110: Bakery | F110: 1 | G110: 274.68 | H110: Mobile
A111: 45441 | B111: R1008 | C111: Westlands | D111: SUGAR | F111: 5 | G111: 436.64 | H111: Card
A112: 45411 | B112: R1067 | C112: Ngong Road | D112: Salt 500g | E112: Grocery | F112: 4 | G112: 283.83 | H112: Mobile
A113: 45368 | B113: R1068 | C113: Westlands | D113: MILK | E113: Dairy | F113: 1 | G113: 141.26 | H113: Card
A114: 45583 | B114: R1073 | C114: Thika Road | D114: Milk 1L | E114: Dairy | F114: 8 | G114: 428.77 | H114: Mobile
A115: 45431 | B115: R1128 | C115: Ngong Road | D115: Eggs Tray | E115: Dairy | F115: 8 | G115: 94.24 | H115: Cash
A116: 45457 | B116: R1154 | C116: Eastlands | D116: Milk | E116: Dairy | F116: 2 | G116: 175.91 | H116: Mobile
A117: 45586 | B117: R1150 | C117: Nairobi CBD | D117: Salt 500g | E117: Grocery | F117: 5 | G117: 366.94 | H117: Cash
A118: 45518 | B118: R1071 | C118: Westlands | D118: Toothpaste | E118: Personal Care | F118: 7 | G118: 399.13 | H118: Card
A119: 45532 | B119: R1089 | C119: Thika Road | D119: Rice | E119: Grocery | F119: 6 | G119: 418.57 | H119: Cash
A120: 45545 | B120: R1073 | C120: Thika Road | D120: Laundry Soap | E120: Household | F120: 1 | G120: 300.15 | H120: Card
A121: 45351 | B121: R1197 | C121: Thika Road | D121: Soap | E121: Household | F121: 1 | G121: 411.71 | H121: Mobile
A122: 45319 | B122: R1048 | C122: Ngong Road | D122: Rice 5kg | E122: Grocery | F122: 10 | G122: 466.04 | H122: Mobile
A123: 45318 | B123: R1052 | C123: Eastlands | D123: Laundry Soap | E123: Household | F123: 3 | G123: 560.22 | H123: Card
... A136: 45460 | B136: R1172 | C136: Ngong Road | D136: Cooking Oil | E136: Grocery | F136: 6 | G136: 394.74 | H136: Card
...
